CHANGELOG.txt
LICENSE.txt
MANIFEST.in
README.txt
setup.py
NeuralNetworkFlow/__init__.py
NeuralNetworkFlow.egg-info/PKG-INFO
NeuralNetworkFlow.egg-info/SOURCES.txt
NeuralNetworkFlow.egg-info/dependency_links.txt
NeuralNetworkFlow.egg-info/requires.txt
NeuralNetworkFlow.egg-info/top_level.txt