Metadata-Version: 2.1
Name: NeuralNetworkFlow
Version: 0.0.1
Summary: Neural Network Data
Home-page: UNKNOWN
Author: PythonCoder2002
Author-email: <adityabijapurkar@gmail.com>
License: UNKNOWN
Keywords: python,neural networks,ann,mcculloh-pitt,ART neural network
Platform: UNKNOWN
Classifier: Development Status :: 1 - Planning
Classifier: Intended Audience :: Developers
Classifier: Programming Language :: Python :: 3
Classifier: Operating System :: Unix
Classifier: Operating System :: MacOS :: MacOS X
Classifier: Operating System :: Microsoft :: Windows
License-File: LICENSE.txt
